pagexml/__init__.py
pagexml/analysis/__init__.py
pagexml/analysis/inventory_stats.py
pagexml/analysis/layout_stats.py
pagexml/analysis/stats.py
pagexml/analysis/text_stats.py
pagexml/column_parser.py
pagexml/helper/__init__.py
pagexml/helper/convert.py
pagexml/helper/file_helper.py
pagexml/helper/pagexml_helper.py
pagexml/helper/spatial_helper.py
pagexml/helper/text_helper.py
pagexml/model/__init__.py
pagexml/model/basic_document_model.py
pagexml/model/coords.py
pagexml/model/empty_model.py
pagexml/model/inventory.py
pagexml/model/logical_document_model.py
pagexml/model/pagexml_document_model.py
pagexml/model/physical_document_model.py
pagexml/model/xml.py
pagexml/parser.py
pagexml/parsers/column_parser.py
pagexml/parsers/scan_parser.py
pagexml/transform/segmentation.py
pagexml_tools-0.8.1.dist-info/LICENSE
pagexml_tools-0.8.1.dist-info/METADATA
pagexml_tools-0.8.1.dist-info/WHEEL
pagexml_tools-0.8.1.dist-info/entry_points.txt
pagexml_tools-0.8.1.dist-info/RECORD
