Metadata-Version: 2.3
Name: pagexml-tools
Version: 0.8.1
Summary: Utility functions for reading PageXML files
License: MIT
Author: Marijn Koolen
Author-email: marijn.koolen@huygens.knaw.nl
Requires-Python: >=3.10,<4.0
Classifier: Development Status :: 4 - Beta
Classifier: Intended Audience :: Science/Research
Classifier: License :: OSI Approved :: MIT License
Classifier: Operating System :: OS Independent
Classifier: Programming Language :: Python :: 3
Classifier: Programming Language :: Python :: 3.10
Classifier: Programming Language :: Python :: 3.11
Classifier: Programming Language :: Python :: 3.12
Classifier: Programming Language :: Python :: 3.13
Classifier: Topic :: Scientific/Engineering
Requires-Dist: fuzzy-search (>=2.4.5,<3.0.0)
Requires-Dist: lxml (>=5.3.0,<6.0.0)
Requires-Dist: numpy (>=1.26,<3.0)
Requires-Dist: py7zr (>=0.20.2,<0.21.0)
Requires-Dist: python-dateutil (>=2.8.2,<3.0.0)
Requires-Dist: pyyaml (>=6.0,<7.0)
Requires-Dist: scipy (>=1.7)
Requires-Dist: shapely (>=2.1.0)
Requires-Dist: tqdm (>=4.64.1,<5.0.0)
Requires-Dist: xmltodict (>=0.13.0,<0.14.0)
Project-URL: Bug Tracker, https://github.com/knaw-huc/pagexml/issues
Project-URL: Homepage, https://github.com/knaw-huc/pagexml
Project-URL: Repository, https://github.com/knaw-huc/pagexml
